translategram/__init__.py
translategram/python_telegram_bot_translator/__init__.py
translategram/python_telegram_bot_translator/adapter.py
translategram/translategram/__init__.py
translategram/translategram/cache.py
translategram/translategram/service_libs.py
translategram/translategram/translator.py
translategram/translategram/translator_services.py
translategram-0.4.0.dist-info/LICENSE
translategram-0.4.0.dist-info/METADATA
translategram-0.4.0.dist-info/WHEEL
translategram-0.4.0.dist-info/top_level.txt
translategram-0.4.0.dist-info/RECORD
