Metadata-Version: 2.1
Name: translategram
Version: 0.4.0
Summary: Translategram is a Python library for translating messages are sent by your Bot in Telegram
Home-page: https://github.com/EkberHasanov/translategram
Author: Akbar
Author-email: hasanvakbar@gmail.com
License: MIT
Classifier: Development Status :: 3 - Alpha
Classifier: Intended Audience :: Developers
Classifier: License :: OSI Approved :: MIT License
Classifier: Programming Language :: Python :: 3
Classifier: Programming Language :: Python :: 3.6
Classifier: Programming Language :: Python :: 3.7
Classifier: Programming Language :: Python :: 3.8
Classifier: Programming Language :: Python :: 3.9
Classifier: Programming Language :: Python :: 3.10
Classifier: Programming Language :: Python :: 3.11
License-File: LICENSE
Requires-Dist: mtranslate
